dismo/__init__.py
dismo/coordinates.py
dismo/grids.py
dismo/models.py
dismo-1.0.58.dist-info/LICENSE
dismo-1.0.58.dist-info/WHEEL
dismo-1.0.58.dist-info/METADATA
dismo-1.0.58.dist-info/RECORD
