Metadata-Version: 2.1
Name: dismo
Version: 1.0.58
Summary: A subpackage of modelbase that enables investigation of PDE models
Author: Marvin van Aalst
Author-email: marvin.vanaalst@gmail.com
Requires-Python: >=3.11,<3.13
Classifier: Programming Language :: Python :: 3
Classifier: Programming Language :: Python :: 3.11
Requires-Dist: matplotlib (>=3.8,<4.0)
Requires-Dist: numpy (>=1.26,<2.0)
Requires-Dist: pandas (>=2.1,<3.0)
Requires-Dist: pyarrow
Requires-Dist: scipy (>=1.12.0,<2.0.0)
Requires-Dist: typing-extensions (>=4.9.0,<5.0.0)
